avp_stream/__init__.py
avp_stream/benchmark_rate.py
avp_stream/bridge_avp.py
avp_stream/calibration_server.py
avp_stream/latency_test.py
avp_stream/plot_benchmarks.py
avp_stream/prepare_calibration.py
avp_stream/run_calibration.py
avp_stream/sim_latency_test.py
avp_stream/streamer.py
avp_stream/verification_engine.py
avp_stream/datasets/__init__.py
avp_stream/datasets/cloudkit.py
avp_stream/datasets/downloaders.py
avp_stream/datasets/models.py
avp_stream/grpc_msg/__init__.py
avp_stream/grpc_msg/handtracking_pb2.py
avp_stream/grpc_msg/handtracking_pb2_grpc.py
avp_stream/mujoco_msg/__init__.py
avp_stream/mujoco_msg/mujoco_ar_pb2.py
avp_stream/mujoco_msg/mujoco_ar_pb2_grpc.py
avp_stream/mujoco_msg/upload_xml.py
avp_stream/utils/__init__.py
avp_stream/utils/grpc_utils.py
avp_stream/utils/isaac_usdz_export.py
avp_stream/utils/isaac_utils.py
avp_stream/utils/latency_benchmark.py
avp_stream/utils/plot_benchmark.py
avp_stream/utils/recording_loader.py
avp_stream/utils/se3_utils.py
avp_stream/utils/trn_constants.py
avp_stream-2.51.dist-info/licenses/LICENSE
avp_stream-2.51.dist-info/METADATA
avp_stream-2.51.dist-info/WHEEL
avp_stream-2.51.dist-info/entry_points.txt
avp_stream-2.51.dist-info/top_level.txt
avp_stream-2.51.dist-info/RECORD
