Metadata-Version: 2.4
Name: avp_stream
Version: 2.51
Summary: This python package streams diverse tracking data available from AVP to any devices that can communicate with gRPC.
Author: Younghyo Park
Author-email: younghyo@mit.edu
License-File: LICENSE
Requires-Dist: numpy
Requires-Dist: grpcio
Requires-Dist: grpcio-tools
Requires-Dist: matplotlib
Requires-Dist: opencv-python
Requires-Dist: aiortc
Requires-Dist: av
Requires-Dist: requests
Requires-Dist: pyyaml
Requires-Dist: mujoco
Requires-Dist: tqdm
Requires-Dist: scipy
Requires-Dist: pydub
Requires-Dist: websocket-client
Requires-Dist: gdown
Requires-Dist: flask
Dynamic: author
Dynamic: author-email
Dynamic: license-file
Dynamic: requires-dist
Dynamic: summary
